<?xml version="1.0" encoding="utf-8" ?>
<dwsync>
<file name="02.jpg" server="50.62.168.3//httpdocs/" local="130583691343735412" remote="130578124200000000" Dst="2" />
<file name="01.jpg" server="50.62.168.3//httpdocs/" local="130583691357264445" remote="130578124200000000" Dst="2" />
<file name="03.jpg" server="50.62.168.3//httpdocs/" local="130583691357994928" remote="130578124200000000" Dst="2" />
<file name="arrows.png" server="50.62.168.3//httpdocs/" local="130583691371994280" remote="130578124200000000" Dst="2" />
<file name="collect1.jpg" server="50.62.168.3//httpdocs/" local="130583691385513273" remote="130578124200000000" Dst="2" />
<file name="3.jpg" server="50.62.168.3//httpdocs/" local="130583691406667410" remote="130578124200000000" Dst="2" />
<file name="dom1.jpg" server="50.62.168.3//httpdocs/" local="130583691407197751" remote="130578124200000000" Dst="2" />
<file name="2.jpg" server="50.62.168.3//httpdocs/" local="130583691420466598" remote="130578124200000000" Dst="2" />
<file name="dom2.jpg" server="50.62.168.3//httpdocs/" local="130583691428121709" remote="130578124200000000" Dst="2" />
<file name="dom3.jpg" server="50.62.168.3//httpdocs/" local="130583691428121709" remote="130578124200000000" Dst="2" />
<file name="facebook.png" server="50.62.168.3//httpdocs/" local="130583691430743445" remote="130578124200000000" Dst="2" />
<file name="gird-img.jpg" server="50.62.168.3//httpdocs/" local="130583691446333931" remote="130578124200000000" Dst="2" />
<file name="gird-img1.jpg" server="50.62.168.3//httpdocs/" local="130583691453188500" remote="130578124200000000" Dst="2" />
<file name="line2.png" server="50.62.168.3//httpdocs/" local="130583691460974027" remote="130578124200000000" Dst="2" />
<file name="gird-img2.jpg" server="50.62.168.3//httpdocs/" local="130583691460974027" remote="130578124200000000" Dst="2" />
<file name="logo.png" server="50.62.168.3//httpdocs/" local="130583691472911990" remote="130578124200000000" Dst="2" />
<file name="logo1.png" server="50.62.168.3//httpdocs/" local="130583691472911990" remote="130578124200000000" Dst="2" />
<file name="nak1.jpg" server="50.62.168.3//httpdocs/" local="130583691486221557" remote="130578124200000000" Dst="2" />
<file name="nak3.jpg" server="50.62.168.3//httpdocs/" local="130583691496168180" remote="130578124200000000" Dst="2" />
<file name="nak2.jpg" server="50.62.168.3//httpdocs/" local="130583691497108803" remote="130578124200000000" Dst="2" />
<file name="nak4.jpg" server="50.62.168.3//httpdocs/" local="130583691509667189" remote="130578124200000000" Dst="2" />
<file name="ring1.jpg" server="50.62.168.3//httpdocs/" local="130583691512119808" remote="130578124200000000" Dst="2" />
<file name="ring3.jpg" server="50.62.168.3//httpdocs/" local="130583691526099129" remote="130578124200000000" Dst="2" />
<file name="ring2.jpg" server="50.62.168.3//httpdocs/" local="130583691526659507" remote="130578124200000000" Dst="2" />
<file name="ring4.jpg" server="50.62.168.3//httpdocs/" local="130583691540618807" remote="130578124200000000" Dst="2" />
<file name="ter-1.jpg" server="50.62.168.3//httpdocs/" local="130583691540989067" remote="130578124200000000" Dst="2" />
<file name="ter-2.jpg" server="50.62.168.3//httpdocs/" local="130583691551205865" remote="130578124200000000" Dst="2" />
<file name="twiter.png" server="50.62.168.3//httpdocs/" local="130583691558220553" remote="130578124200000000" Dst="2" />
<file name="Thumbs.db" server="50.62.168.3//httpdocs/" local="130583691559521417" remote="130578124200000000" Dst="2" />
<file name="video.png" server="50.62.168.3//httpdocs/" local="130583691575882327" remote="130578124200000000" Dst="2" />
</dwsync>